<image>
  <image-id>2346949</image-id>
  <coco-id>281663</coco-id>
  <relationships>
    <relationship>
      <relationship_id>4743209</relationship_id>
      <predicate>eating a</predicate>
      <subject>4449026</subject>
      <object>4449027</object>
    </relationship>
    <relationship>
      <relationship_id>4743210</relationship_id>
      <predicate>used as a</predicate>
      <subject>4449059</subject>
      <object>4449029</object>
    </relationship>
    <relationship>
      <relationship_id>4743211</relationship_id>
      <predicate>used as a</predicate>
      <subject>4449031</subject>
      <object>4449030</object>
    </relationship>
    <relationship>
      <relationship_id>4743212</relationship_id>
      <predicate>in a</predicate>
      <subject>4449082</subject>
      <object>4449033</object>
    </relationship>
    <relationship>
      <relationship_id>4743213</relationship_id>
      <predicate>under</predicate>
      <subject>4449035</subject>
      <object>4449034</object>
    </relationship>
    <relationship>
      <relationship_id>4743214</relationship_id>
      <predicate>are on a</predicate>
      <subject>4449037</subject>
      <object>4449026</object>
    </relationship>
    <relationship>
      <relationship_id>4743215</relationship_id>
      <predicate>on a</predicate>
      <subject>4449039</subject>
      <object>4449026</object>
    </relationship>
    <relationship>
      <relationship_id>4743217</relationship_id>
      <predicate>has a</predicate>
      <subject>4449026</subject>
      <object>4449042</object>
    </relationship>
    <relationship>
      <relationship_id>4743216</relationship_id>
      <predicate>around</predicate>
      <subject>4449042</subject>
      <object>4449043</object>
    </relationship>
    <relationship>
      <relationship_id>4743218</relationship_id>
      <predicate>on</predicate>
      <subject>4449044</subject>
      <object>4449026</object>
    </relationship>
    <relationship>
      <relationship_id>4743219</relationship_id>
      <predicate>eating</predicate>
      <subject>4449026</subject>
      <object>4449059</object>
    </relationship>
    <relationship>
      <relationship_id>4743220</relationship_id>
      <predicate>wearing</predicate>
      <subject>4449026</subject>
      <object>4449037</object>
    </relationship>
    <relationship>
      <relationship_id>4743221</relationship_id>
      <predicate>wearing</predicate>
      <subject>4449026</subject>
      <object>4449051</object>
    </relationship>
    <relationship>
      <relationship_id>4743222</relationship_id>
      <predicate>standing near</predicate>
      <subject>4449053</subject>
      <object>4449054</object>
    </relationship>
    <relationship>
      <relationship_id>4743223</relationship_id>
      <predicate>OF</predicate>
      <subject>4449055</subject>
      <object>4449026</object>
    </relationship>
    <relationship>
      <relationship_id>4743224</relationship_id>
      <predicate>OF</predicate>
      <subject>4449058</subject>
      <object>4449026</object>
    </relationship>
    <relationship>
      <relationship_id>4743225</relationship_id>
      <predicate>with</predicate>
      <subject>4449059</subject>
      <object>4449060</object>
    </relationship>
    <relationship>
      <relationship_id>4743226</relationship_id>
      <predicate>OF</predicate>
      <subject>4449061</subject>
      <object>4449026</object>
    </relationship>
    <relationship>
      <relationship_id>4743227</relationship_id>
      <predicate>OF</predicate>
      <subject>4449064</subject>
      <object>4449026</object>
    </relationship>
    <relationship>
      <relationship_id>4743228</relationship_id>
      <predicate>eating</predicate>
      <subject>4449065</subject>
      <object>4449066</object>
    </relationship>
    <relationship>
      <relationship_id>4743229</relationship_id>
      <predicate>stuffing</predicate>
      <subject>4449077</subject>
      <object>4449068</object>
    </relationship>
    <relationship>
      <relationship_id>4743230</relationship_id>
      <predicate>ON</predicate>
      <subject>4449082</subject>
      <object>4449070</object>
    </relationship>
    <relationship>
      <relationship_id>4743231</relationship_id>
      <predicate>WEARING</predicate>
      <subject>4449077</subject>
      <object>4449076</object>
    </relationship>
    <relationship>
      <relationship_id>4743232</relationship_id>
      <predicate>has</predicate>
      <subject>4449077</subject>
      <object>4449078</object>
    </relationship>
    <relationship>
      <relationship_id>4743233</relationship_id>
      <predicate>eating</predicate>
      <subject>4449026</subject>
      <object>4449080</object>
    </relationship>
    <relationship>
      <relationship_id>4743234</relationship_id>
      <predicate>IN</predicate>
      <subject>4449082</subject>
      <object>4449081</object>
    </relationship>
    <relationship>
      <relationship_id>4743235</relationship_id>
      <predicate>ON</predicate>
      <subject>4449083</subject>
      <object>4449026</object>
    </relationship>
    <relationship>
      <relationship_id>4743236</relationship_id>
      <predicate>ON</predicate>
      <subject>4449089</subject>
      <object>4449058</object>
    </relationship>
    <relationship>
      <relationship_id>4743237</relationship_id>
      <predicate>ON</predicate>
      <subject>4449093</subject>
      <object>4449094</object>
    </relationship>
  </relationships>
  <objects>
    <object>
      <name>woman</name>
      <h>350</h>
      <object_id>4449026</object_id>
      <w>442</w>
      <y>20</y>
      <x>34</x>
    </object>
    <object>
      <attributes>
        <attribute>unhealthy </attribute>
      </attributes>
      <name>sandwich</name>
      <h>87</h>
      <object_id>4449027</object_id>
      <w>151</w>
      <y>178</y>
      <x>148</x>
    </object>
    <object>
      <attributes>
        <attribute>Brown color </attribute>
      </attributes>
      <h>75</h>
      <object_id>4449059</object_id>
      <w>167</w>
      <y>161</y>
      <x>129</x>
      <name>donuts</name>
    </object>
    <object>
      <name>bun</name>
      <h>27</h>
      <object_id>4449029</object_id>
      <w>50</w>
      <y>183</y>
      <x>198</x>
    </object>
    <object>
      <name>doughnut</name>
      <h>9</h>
      <object_id>4449031</object_id>
      <w>31</w>
      <y>257</y>
      <x>236</x>
    </object>
    <object>
      <name>bun</name>
      <h>11</h>
      <object_id>4449030</object_id>
      <w>27</w>
      <y>237</y>
      <x>283</x>
    </object>
    <object>
      <attributes>
        <attribute>purple </attribute>
      </attributes>
      <h>54</h>
      <object_id>4449082</object_id>
      <w>134</w>
      <y>204</y>
      <x>164</x>
      <name>onion</name>
    </object>
    <object>
      <name>sandwhich</name>
      <h>80</h>
      <object_id>4449033</object_id>
      <w>155</w>
      <y>178</y>
      <x>151</x>
    </object>
    <object>
      <attributes>
        <attribute>white</attribute>
      </attributes>
      <name>paper</name>
      <h>81</h>
      <object_id>4449035</object_id>
      <w>94</w>
      <y>285</y>
      <x>212</x>
    </object>
    <object>
      <name>sandwhich</name>
      <h>79</h>
      <object_id>4449034</object_id>
      <w>167</w>
      <y>180</y>
      <x>142</x>
    </object>
    <object>
      <attributes>
        <attribute>dark</attribute>
      </attributes>
      <name>glasses</name>
      <h>107</h>
      <object_id>4449037</object_id>
      <w>195</w>
      <y>30</y>
      <x>121</x>
    </object>
    <object>
      <name>earring</name>
      <h>75</h>
      <object_id>4449039</object_id>
      <w>43</w>
      <y>153</y>
      <x>386</x>
    </object>
    <object>
      <name>chain</name>
      <h>53</h>
      <object_id>4449042</object_id>
      <w>27</w>
      <y>247</y>
      <x>426</x>
    </object>
    <object>
      <name>neck</name>
      <h>70</h>
      <object_id>4449043</object_id>
      <w>42</w>
      <y>223</y>
      <x>388</x>
    </object>
    <object>
      <attributes>
        <attribute>tan</attribute>
      </attributes>
      <name>sweater</name>
      <h>18</h>
      <object_id>4449044</object_id>
      <w>10</w>
      <y>341</y>
      <x>474</x>
    </object>
    <object>
      <name>earring</name>
      <h>70</h>
      <object_id>4449051</object_id>
      <w>47</w>
      <y>153</y>
      <x>382</x>
    </object>
    <object>
      <name>person</name>
      <h>73</h>
      <object_id>4449053</object_id>
      <w>82</w>
      <y>82</y>
      <x>16</x>
    </object>
    <object>
      <name>building</name>
      <h>43</h>
      <object_id>4449054</object_id>
      <w>48</w>
      <y>30</y>
      <x>44</x>
    </object>
    <object>
      <name>head</name>
      <h>262</h>
      <object_id>4449055</object_id>
      <w>341</w>
      <y>3</y>
      <x>96</x>
    </object>
    <object>
      <attributes>
        <attribute>woman's  </attribute>
      </attributes>
      <name>hand</name>
      <h>194</h>
      <object_id>4449058</object_id>
      <w>241</w>
      <y>161</y>
      <x>33</x>
    </object>
    <object>
      <name>napkin</name>
      <h>130</h>
      <object_id>4449060</object_id>
      <w>286</w>
      <y>240</y>
      <x>160</x>
    </object>
    <object>
      <name>nose</name>
      <h>82</h>
      <object_id>4449061</object_id>
      <w>64</w>
      <y>84</y>
      <x>178</x>
    </object>
    <object>
      <name>neck</name>
      <h>150</h>
      <object_id>4449064</object_id>
      <w>101</w>
      <y>151</y>
      <x>338</x>
    </object>
    <object>
      <name>lady</name>
      <h>367</h>
      <object_id>4449065</object_id>
      <w>470</w>
      <y>0</y>
      <x>11</x>
    </object>
    <object>
      <attributes>
        <attribute>under</attribute>
      </attributes>
      <name>sandwich</name>
      <h>134</h>
      <object_id>4449066</object_id>
      <w>192</w>
      <y>150</y>
      <x>126</x>
    </object>
    <object>
      <h>375</h>
      <object_id>4449077</object_id>
      <w>500</w>
      <y>0</y>
      <x>0</x>
      <name>she</name>
    </object>
    <object>
      <name>mouth</name>
      <h>98</h>
      <object_id>4449068</object_id>
      <w>162</w>
      <y>160</y>
      <x>148</x>
    </object>
    <object>
      <name>sandwich</name>
      <h>125</h>
      <object_id>4449070</object_id>
      <w>224</w>
      <y>147</y>
      <x>129</x>
    </object>
    <object>
      <attributes>
        <attribute>skull </attribute>
      </attributes>
      <name>earrings</name>
      <h>100</h>
      <object_id>4449076</object_id>
      <w>50</w>
      <y>131</y>
      <x>377</x>
    </object>
    <object>
      <name>necklace</name>
      <h>203</h>
      <object_id>4449078</object_id>
      <w>83</w>
      <y>170</y>
      <x>391</x>
    </object>
    <object>
      <name>sandwich</name>
      <h>139</h>
      <object_id>4449080</object_id>
      <w>186</w>
      <y>155</y>
      <x>124</x>
    </object>
    <object>
      <name>sandwich</name>
      <h>127</h>
      <object_id>4449081</object_id>
      <w>189</w>
      <y>155</y>
      <x>120</x>
    </object>
    <object>
      <attributes>
        <attribute>gold </attribute>
      </attributes>
      <name>necklace</name>
      <h>207</h>
      <object_id>4449083</object_id>
      <w>102</w>
      <y>166</y>
      <x>373</x>
    </object>
    <object>
      <name>knuckle</name>
      <h>105</h>
      <object_id>4449089</object_id>
      <w>110</w>
      <y>251</y>
      <x>70</x>
    </object>
    <object>
      <name>nose</name>
      <h>73</h>
      <object_id>4449093</object_id>
      <w>80</w>
      <y>86</y>
      <x>169</x>
    </object>
    <object>
      <attributes>
        <attribute>woman's </attribute>
      </attributes>
      <name>face</name>
      <h>275</h>
      <object_id>4449094</object_id>
      <w>301</w>
      <y>27</y>
      <x>102</x>
    </object>
  </objects>
  <captions type="train">
    <caption>A woman sinks her teeth into a hamburger.</caption>
      <caption>A girl eating a hamburger with her right hand.</caption>
      <caption>A large woman stuffing her face with a sandwich.</caption>
      <caption>Woman eating a burger out in the sun.</caption>
      <caption>A woman eats a hamburger outside with others.</caption>
    </captions>
</image>