<image>
  <image-id>2356750</image-id>
  <coco-id>372471</coco-id>
  <relationships>
    <relationship>
      <relationship_id>2301646</relationship_id>
      <predicate>has</predicate>
      <subject>817630</subject>
      <object>817631</object>
    </relationship>
    <relationship>
      <relationship_id>2301647</relationship_id>
      <predicate>has</predicate>
      <subject>817630</subject>
      <object>817632</object>
    </relationship>
    <relationship>
      <relationship_id>2301648</relationship_id>
      <predicate>has</predicate>
      <subject>817630</subject>
      <object>817633</object>
    </relationship>
    <relationship>
      <relationship_id>2301649</relationship_id>
      <predicate>made from</predicate>
      <subject>817635</subject>
      <object>817635</object>
    </relationship>
    <relationship>
      <relationship_id>2301650</relationship_id>
      <predicate>part of</predicate>
      <subject>817635</subject>
      <object>817636</object>
    </relationship>
    <relationship>
      <relationship_id>2301651</relationship_id>
      <predicate>made from</predicate>
      <subject>817635</subject>
      <object>817638</object>
    </relationship>
    <relationship>
      <relationship_id>2301652</relationship_id>
      <predicate>part of</predicate>
      <subject>817635</subject>
      <object>817636</object>
    </relationship>
    <relationship>
      <relationship_id>2301653</relationship_id>
      <predicate>part of</predicate>
      <subject>817639</subject>
      <object>817636</object>
    </relationship>
    <relationship>
      <relationship_id>2301654</relationship_id>
      <predicate>made from</predicate>
      <subject>817635</subject>
      <object>817635</object>
    </relationship>
    <relationship>
      <relationship_id>2301655</relationship_id>
      <predicate>part of</predicate>
      <subject>817635</subject>
      <object>817636</object>
    </relationship>
    <relationship>
      <relationship_id>2301656</relationship_id>
      <predicate>made from</predicate>
      <subject>817635</subject>
      <object>817638</object>
    </relationship>
    <relationship>
      <relationship_id>2301657</relationship_id>
      <predicate>part of</predicate>
      <subject>817635</subject>
      <object>817636</object>
    </relationship>
    <relationship>
      <relationship_id>2301658</relationship_id>
      <predicate>part of</predicate>
      <subject>817639</subject>
      <object>817636</object>
    </relationship>
    <relationship>
      <relationship_id>2301659</relationship_id>
      <predicate>made from</predicate>
      <subject>817641</subject>
      <object>817641</object>
    </relationship>
    <relationship>
      <relationship_id>2301660</relationship_id>
      <predicate>part of</predicate>
      <subject>817641</subject>
      <object>817636</object>
    </relationship>
    <relationship>
      <relationship_id>2301661</relationship_id>
      <predicate>made from</predicate>
      <subject>817643</subject>
      <object>817643</object>
    </relationship>
    <relationship>
      <relationship_id>2301662</relationship_id>
      <predicate>part of</predicate>
      <subject>817643</subject>
      <object>817636</object>
    </relationship>
    <relationship>
      <relationship_id>2301663</relationship_id>
      <predicate>part of</predicate>
      <subject>817644</subject>
      <object>817636</object>
    </relationship>
    <relationship>
      <relationship_id>2301664</relationship_id>
      <predicate>has a</predicate>
      <subject>817636</subject>
      <object>817645</object>
    </relationship>
    <relationship>
      <relationship_id>2301665</relationship_id>
      <predicate>has a</predicate>
      <subject>817636</subject>
      <object>817646</object>
    </relationship>
    <relationship>
      <relationship_id>2301666</relationship_id>
      <predicate>has a</predicate>
      <subject>817636</subject>
      <object>817645</object>
    </relationship>
    <relationship>
      <relationship_id>2301667</relationship_id>
      <predicate>has a</predicate>
      <subject>817636</subject>
      <object>817646</object>
    </relationship>
    <relationship>
      <relationship_id>2301668</relationship_id>
      <predicate>says</predicate>
      <subject>817628</subject>
      <object>817648</object>
    </relationship>
    <relationship>
      <relationship_id>2301669</relationship_id>
      <predicate>made of</predicate>
      <subject>817636</subject>
      <object>817651</object>
    </relationship>
    <relationship>
      <relationship_id>2301670</relationship_id>
      <predicate>made of</predicate>
      <subject>817636</subject>
      <object>817652</object>
    </relationship>
    <relationship>
      <relationship_id>2301671</relationship_id>
      <predicate>made of</predicate>
      <subject>817636</subject>
      <object>817654</object>
    </relationship>
    <relationship>
      <relationship_id>2301672</relationship_id>
      <predicate>made of</predicate>
      <subject>817636</subject>
      <object>817656</object>
    </relationship>
    <relationship>
      <relationship_id>2301673</relationship_id>
      <predicate>contains</predicate>
      <subject>817628</subject>
      <object>817657</object>
    </relationship>
    <relationship>
      <relationship_id>2301674</relationship_id>
      <predicate>contains</predicate>
      <subject>817628</subject>
      <object>817658</object>
    </relationship>
    <relationship>
      <relationship_id>2301675</relationship_id>
      <predicate>contains</predicate>
      <subject>817628</subject>
      <object>817659</object>
    </relationship>
    <relationship>
      <relationship_id>2301676</relationship_id>
      <predicate>contains</predicate>
      <subject>817630</subject>
      <object>817649</object>
    </relationship>
    <relationship>
      <relationship_id>2301677</relationship_id>
      <predicate>has</predicate>
      <subject>817647</subject>
      <object>817631</object>
    </relationship>
    <relationship>
      <relationship_id>2301678</relationship_id>
      <predicate>has</predicate>
      <subject>817647</subject>
      <object>817632</object>
    </relationship>
    <relationship>
      <relationship_id>2301679</relationship_id>
      <predicate>has</predicate>
      <subject>817647</subject>
      <object>817633</object>
    </relationship>
    <relationship>
      <relationship_id>2301680</relationship_id>
      <predicate>part of</predicate>
      <subject>817635</subject>
      <object>817636</object>
    </relationship>
    <relationship>
      <relationship_id>2301681</relationship_id>
      <predicate>part of</predicate>
      <subject>817639</subject>
      <object>817636</object>
    </relationship>
    <relationship>
      <relationship_id>2301682</relationship_id>
      <predicate>part of</predicate>
      <subject>817635</subject>
      <object>817636</object>
    </relationship>
    <relationship>
      <relationship_id>2301683</relationship_id>
      <predicate>part of</predicate>
      <subject>817641</subject>
      <object>817636</object>
    </relationship>
    <relationship>
      <relationship_id>2301684</relationship_id>
      <predicate>part of</predicate>
      <subject>817644</subject>
      <object>817636</object>
    </relationship>
    <relationship>
      <relationship_id>2301685</relationship_id>
      <predicate>contains</predicate>
      <subject>817628</subject>
      <object>817657</object>
    </relationship>
    <relationship>
      <relationship_id>2301686</relationship_id>
      <predicate>of a</predicate>
      <subject>817660</subject>
      <object>817636</object>
    </relationship>
    <relationship>
      <relationship_id>2301687</relationship_id>
      <predicate>of a</predicate>
      <subject>817661</subject>
      <object>817636</object>
    </relationship>
    <relationship>
      <relationship_id>2301688</relationship_id>
      <predicate>says</predicate>
      <subject>817628</subject>
      <object>817662</object>
    </relationship>
    <relationship>
      <relationship_id>2301689</relationship_id>
      <predicate>has</predicate>
      <subject>817636</subject>
      <object>817635</object>
    </relationship>
    <relationship>
      <relationship_id>2301692</relationship_id>
      <predicate>has</predicate>
      <subject>817636</subject>
      <object>817639</object>
    </relationship>
    <relationship>
      <relationship_id>2301693</relationship_id>
      <predicate>has</predicate>
      <subject>817636</subject>
      <object>817644</object>
    </relationship>
    <relationship>
      <relationship_id>2301690</relationship_id>
      <predicate>has</predicate>
      <subject>817636</subject>
      <object>817663</object>
    </relationship>
    <relationship>
      <relationship_id>2301691</relationship_id>
      <predicate>has</predicate>
      <subject>817636</subject>
      <object>817664</object>
    </relationship>
    <relationship>
      <relationship_id>2301694</relationship_id>
      <predicate>has</predicate>
      <subject>817628</subject>
      <object>817658</object>
    </relationship>
    <relationship>
      <relationship_id>2301695</relationship_id>
      <predicate>made of</predicate>
      <subject>817636</subject>
      <object>817651</object>
    </relationship>
    <relationship>
      <relationship_id>2301696</relationship_id>
      <predicate>made of</predicate>
      <subject>817636</subject>
      <object>817652</object>
    </relationship>
    <relationship>
      <relationship_id>2301697</relationship_id>
      <predicate>made of</predicate>
      <subject>817636</subject>
      <object>817654</object>
    </relationship>
    <relationship>
      <relationship_id>2301698</relationship_id>
      <predicate>made of</predicate>
      <subject>817636</subject>
      <object>817656</object>
    </relationship>
    <relationship>
      <relationship_id>2301699</relationship_id>
      <predicate>contains</predicate>
      <subject>817628</subject>
      <object>817648</object>
    </relationship>
    <relationship>
      <relationship_id>2301700</relationship_id>
      <predicate>contains</predicate>
      <subject>817628</subject>
      <object>817665</object>
    </relationship>
    <relationship>
      <relationship_id>2301701</relationship_id>
      <predicate>has</predicate>
      <subject>817630</subject>
      <object>817633</object>
    </relationship>
    <relationship>
      <relationship_id>2301702</relationship_id>
      <predicate>has</predicate>
      <subject>817630</subject>
      <object>817649</object>
    </relationship>
    <relationship>
      <relationship_id>2301703</relationship_id>
      <predicate>holding</predicate>
      <subject>817647</subject>
      <object>817628</object>
    </relationship>
    <relationship>
      <relationship_id>2301704</relationship_id>
      <predicate>holding</predicate>
      <subject>817647</subject>
      <object>817629</object>
    </relationship>
    <relationship>
      <relationship_id>2301705</relationship_id>
      <predicate>holding</predicate>
      <subject>817647</subject>
      <object>817630</object>
    </relationship>
    <relationship>
      <relationship_id>2301706</relationship_id>
      <predicate>on side of</predicate>
      <subject>817645</subject>
      <object>817636</object>
    </relationship>
    <relationship>
      <relationship_id>2301707</relationship_id>
      <predicate>on side of</predicate>
      <subject>817646</subject>
      <object>817636</object>
    </relationship>
    <relationship>
      <relationship_id>2301708</relationship_id>
      <predicate>has</predicate>
      <subject>817645</subject>
      <object>817666</object>
    </relationship>
    <relationship>
      <relationship_id>2301709</relationship_id>
      <predicate>made from</predicate>
      <subject>817636</subject>
      <object>817651</object>
    </relationship>
    <relationship>
      <relationship_id>2301710</relationship_id>
      <predicate>has</predicate>
      <subject>817636</subject>
      <object>817635</object>
    </relationship>
    <relationship>
      <relationship_id>2301713</relationship_id>
      <predicate>has</predicate>
      <subject>817636</subject>
      <object>817644</object>
    </relationship>
    <relationship>
      <relationship_id>2301711</relationship_id>
      <predicate>made from</predicate>
      <subject>817636</subject>
      <object>817654</object>
    </relationship>
    <relationship>
      <relationship_id>2301712</relationship_id>
      <predicate>made from</predicate>
      <subject>817636</subject>
      <object>817656</object>
    </relationship>
    <relationship>
      <relationship_id>2301714</relationship_id>
      <predicate>says</predicate>
      <subject>817628</subject>
      <object>817648</object>
    </relationship>
    <relationship>
      <relationship_id>2301715</relationship_id>
      <predicate>made from</predicate>
      <subject>817636</subject>
      <object>817652</object>
    </relationship>
    <relationship>
      <relationship_id>2301716</relationship_id>
      <predicate>made from</predicate>
      <subject>817636</subject>
      <object>817651</object>
    </relationship>
    <relationship>
      <relationship_id>2301717</relationship_id>
      <predicate>made from</predicate>
      <subject>817636</subject>
      <object>817654</object>
    </relationship>
    <relationship>
      <relationship_id>2301718</relationship_id>
      <predicate>made from</predicate>
      <subject>817636</subject>
      <object>817656</object>
    </relationship>
  </relationships>
  <objects>
    <object>
      <name>traffic light</name>
      <h>144</h>
      <object_id>817630</object_id>
      <w>59</w>
      <y>122</y>
      <x>150</x>
    </object>
    <object>
      <name>indicator</name>
      <h>41</h>
      <object_id>817631</object_id>
      <w>46</w>
      <y>128</y>
      <x>159</x>
    </object>
    <object>
      <name>indicator</name>
      <h>39</h>
      <object_id>817632</object_id>
      <w>41</w>
      <y>175</y>
      <x>164</x>
    </object>
    <object>
      <attributes>
        <attribute>green</attribute>
      </attributes>
      <name>indicator</name>
      <h>41</h>
      <object_id>817633</object_id>
      <w>46</w>
      <y>220</y>
      <x>159</x>
    </object>
    <object>
      <h>51</h>
      <object_id>817635</object_id>
      <w>30</w>
      <y>14</y>
      <x>330</x>
      <name>glass</name>
    </object>
    <object>
      <name>building</name>
      <h>329</h>
      <object_id>817636</object_id>
      <w>286</w>
      <y>1</y>
      <x>211</x>
    </object>
    <object>
      <name>glass</name>
      <h>27</h>
      <object_id>817638</object_id>
      <w>28</w>
      <y>38</y>
      <x>333</x>
    </object>
    <object>
      <name>window</name>
      <h>22</h>
      <object_id>817639</object_id>
      <w>33</w>
      <y>1</y>
      <x>409</x>
    </object>
    <object>
      <h>125</h>
      <object_id>817641</object_id>
      <w>31</w>
      <y>208</y>
      <x>247</x>
      <name>glass</name>
    </object>
    <object>
      <h>137</h>
      <object_id>817643</object_id>
      <w>38</w>
      <y>161</y>
      <x>314</x>
      <name>glass</name>
    </object>
    <object>
      <name>window</name>
      <h>129</h>
      <object_id>817644</object_id>
      <w>37</w>
      <y>127</y>
      <x>402</x>
    </object>
    <object>
      <attributes>
        <attribute>wired</attribute>
        <attribute>black</attribute>
      </attributes>
      <name>balcony</name>
      <h>112</h>
      <object_id>817645</object_id>
      <w>106</w>
      <y>146</y>
      <x>394</x>
    </object>
    <object>
      <attributes>
        <attribute>wired</attribute>
        <attribute>black</attribute>
      </attributes>
      <name>balcony</name>
      <h>45</h>
      <object_id>817646</object_id>
      <w>113</w>
      <y>286</y>
      <x>166</x>
    </object>
    <object>
      <attributes>
        <attribute>green</attribute>
        <attribute>white</attribute>
      </attributes>
      <name>sign post</name>
      <h>75</h>
      <object_id>817628</object_id>
      <w>192</w>
      <y>61</y>
      <x>278</x>
    </object>
    <object>
      <attributes>
        <attribute>white</attribute>
      </attributes>
      <name>s gay st</name>
      <h>41</h>
      <object_id>817648</object_id>
      <w>93</w>
      <y>75</y>
      <x>300</x>
    </object>
    <object>
      <name>bricks</name>
      <h>296</h>
      <object_id>817651</object_id>
      <w>286</w>
      <y>33</y>
      <x>214</x>
    </object>
    <object>
      <name>bricks</name>
      <h>65</h>
      <object_id>817652</object_id>
      <w>97</w>
      <y>0</y>
      <x>317</x>
    </object>
    <object>
      <name>bricks</name>
      <h>286</h>
      <object_id>817654</object_id>
      <w>296</w>
      <y>46</y>
      <x>9</x>
    </object>
    <object>
      <name>bricks</name>
      <h>150</h>
      <object_id>817656</object_id>
      <w>204</w>
      <y>35</y>
      <x>1</x>
    </object>
    <object>
      <attributes>
        <attribute>300</attribute>
      </attributes>
      <name>number</name>
      <h>17</h>
      <object_id>817657</object_id>
      <w>30</w>
      <y>102</y>
      <x>386</x>
    </object>
    <object>
      <attributes>
        <attribute>white</attribute>
      </attributes>
      <name>arrow</name>
      <h>15</h>
      <object_id>817658</object_id>
      <w>21</w>
      <y>104</y>
      <x>429</x>
    </object>
    <object>
      <attributes>
        <attribute>white</attribute>
      </attributes>
      <name>border</name>
      <h>73</h>
      <object_id>817659</object_id>
      <w>187</w>
      <y>60</y>
      <x>281</x>
    </object>
    <object>
      <attributes>
        <attribute>green</attribute>
        <attribute>lit</attribute>
      </attributes>
      <name>arrow</name>
      <h>30</h>
      <object_id>817649</object_id>
      <w>23</w>
      <y>226</y>
      <x>168</x>
    </object>
    <object>
      <attributes>
        <attribute>metallic</attribute>
        <attribute>black</attribute>
      </attributes>
      <name>sign pole</name>
      <h>44</h>
      <object_id>817647</object_id>
      <w>498</w>
      <y>66</y>
      <x>1</x>
    </object>
    <object>
      <name>top</name>
      <h>32</h>
      <object_id>817660</object_id>
      <w>200</w>
      <y>32</y>
      <x>3</x>
    </object>
    <object>
      <name>top</name>
      <h>76</h>
      <object_id>817661</object_id>
      <w>197</w>
      <y>40</y>
      <x>107</x>
    </object>
    <object>
      <name>gay st</name>
      <h>44</h>
      <object_id>817662</object_id>
      <w>76</w>
      <y>74</y>
      <x>319</x>
    </object>
    <object>
      <name>windows</name>
      <h>78</h>
      <object_id>817663</object_id>
      <w>89</w>
      <y>233</y>
      <x>65</x>
    </object>
    <object>
      <name>window</name>
      <h>27</h>
      <object_id>817664</object_id>
      <w>11</w>
      <y>110</y>
      <x>2</x>
    </object>
    <object>
      <attributes>
        <attribute>white</attribute>
      </attributes>
      <name>letters</name>
      <h>15</h>
      <object_id>817665</object_id>
      <w>21</w>
      <y>83</y>
      <x>428</x>
    </object>
    <object>
      <attributes>
        <attribute>white</attribute>
        <attribute>hanging</attribute>
        <attribute>black</attribute>
      </attributes>
      <name>sign post</name>
      <h>125</h>
      <object_id>817629</object_id>
      <w>106</w>
      <y>118</y>
      <x>41</x>
    </object>
    <object>
      <attributes>
        <attribute>dark</attribute>
        <attribute>metal</attribute>
      </attributes>
      <name>railing</name>
      <h>35</h>
      <object_id>817666</object_id>
      <w>106</w>
      <y>146</y>
      <x>393</x>
    </object>
  </objects>
  <captions type="train">
    <caption>A left turn signal, stoplight and street sign are hanging on a pole.</caption>
      <caption>A traffic light in a city with two signs on either side of it.</caption>
      <caption>A left turn sign is by a street sign.</caption>
      <caption>A large street sign on a pole over a street.</caption>
      <caption>a close up of a street sign near a traffic light</caption>
    </captions>
</image>