<image>
  <image-id>2360803</image-id>
  <coco-id>219905</coco-id>
  <relationships>
    <relationship>
      <relationship_id>4198148</relationship_id>
      <predicate>ON</predicate>
      <subject>2138106</subject>
      <object>3483999</object>
    </relationship>
    <relationship>
      <relationship_id>4198149</relationship_id>
      <predicate>ON</predicate>
      <subject>3003937</subject>
      <object>3759021</object>
    </relationship>
    <relationship>
      <relationship_id>4198150</relationship_id>
      <predicate>ON</predicate>
      <subject>2862098</subject>
      <object>2949911</object>
    </relationship>
    <relationship>
      <relationship_id>4198151</relationship_id>
      <predicate>ON</predicate>
      <subject>2862102</subject>
      <object>3759016</object>
    </relationship>
    <relationship>
      <relationship_id>4198152</relationship_id>
      <predicate>under</predicate>
      <subject>3759024</subject>
      <object>2862100</object>
    </relationship>
    <relationship>
      <relationship_id>3914619</relationship_id>
      <predicate>under</predicate>
      <subject>2135808</subject>
      <object>2862098</object>
    </relationship>
    <relationship>
      <relationship_id>4198153</relationship_id>
      <predicate>ON</predicate>
      <subject>2138106</subject>
      <object>3483999</object>
    </relationship>
    <relationship>
      <relationship_id>4198154</relationship_id>
      <predicate>ON</predicate>
      <subject>2623589</subject>
      <object>3759032</object>
    </relationship>
    <relationship>
      <relationship_id>4198155</relationship_id>
      <predicate>IN</predicate>
      <subject>2430348</subject>
      <object>2430349</object>
    </relationship>
    <relationship>
      <relationship_id>4198156</relationship_id>
      <predicate>ON</predicate>
      <subject>3759018</subject>
      <object>2619141</object>
    </relationship>
    <relationship>
      <relationship_id>4198157</relationship_id>
      <predicate>ON</predicate>
      <subject>3759019</subject>
      <object>2315142</object>
    </relationship>
    <relationship>
      <relationship_id>4198161</relationship_id>
      <predicate>with</predicate>
      <subject>3759025</subject>
      <object>2949207</object>
    </relationship>
    <relationship>
      <relationship_id>4198160</relationship_id>
      <predicate>with</predicate>
      <subject>3759023</subject>
      <object>3759024</object>
    </relationship>
    <relationship>
      <relationship_id>4198159</relationship_id>
      <predicate>with</predicate>
      <subject>3759021</subject>
      <object>3759022</object>
    </relationship>
    <relationship>
      <relationship_id>4198158</relationship_id>
      <predicate>with</predicate>
      <subject>2949207</subject>
      <object>3759020</object>
    </relationship>
    <relationship>
      <relationship_id>4198162</relationship_id>
      <predicate>ON</predicate>
      <subject>2176294</subject>
      <object>3323943</object>
    </relationship>
    <relationship>
      <relationship_id>4198163</relationship_id>
      <predicate>ON</predicate>
      <subject>2135807</subject>
      <object>2135808</object>
    </relationship>
    <relationship>
      <relationship_id>4198165</relationship_id>
      <predicate>inside of</predicate>
      <subject>3759035</subject>
      <object>1794390</object>
    </relationship>
    <relationship>
      <relationship_id>4198164</relationship_id>
      <predicate>ON</predicate>
      <subject>3493390</subject>
      <object>3759035</object>
    </relationship>
    <relationship>
      <relationship_id>4198166</relationship_id>
      <predicate>ON</predicate>
      <subject>3759027</subject>
      <object>2163548</object>
    </relationship>
    <relationship>
      <relationship_id>3818954</relationship_id>
      <predicate>ON</predicate>
      <subject>3514471</subject>
      <object>3514470</object>
    </relationship>
    <relationship>
      <relationship_id>3818955</relationship_id>
      <predicate>ON</predicate>
      <subject>3514472</subject>
      <object>3514470</object>
    </relationship>
    <relationship>
      <relationship_id>4198167</relationship_id>
      <predicate>ON</predicate>
      <subject>3759028</subject>
      <object>2891655</object>
    </relationship>
    <relationship>
      <relationship_id>4198168</relationship_id>
      <predicate>ON</predicate>
      <subject>3361675</subject>
      <object>3361674</object>
    </relationship>
    <relationship>
      <relationship_id>4198169</relationship_id>
      <predicate>hanging on</predicate>
      <subject>1665820</subject>
      <object>2619141</object>
    </relationship>
    <relationship>
      <relationship_id>4198170</relationship_id>
      <predicate>ON</predicate>
      <subject>2862098</subject>
      <object>2862097</object>
    </relationship>
    <relationship>
      <relationship_id>4198171</relationship_id>
      <predicate>ON</predicate>
      <subject>1665820</subject>
      <object>2862097</object>
    </relationship>
    <relationship>
      <relationship_id>4198172</relationship_id>
      <predicate>ON</predicate>
      <subject>2862100</subject>
      <object>2862097</object>
    </relationship>
    <relationship>
      <relationship_id>4198173</relationship_id>
      <predicate>ON</predicate>
      <subject>2862101</subject>
      <object>2862097</object>
    </relationship>
    <relationship>
      <relationship_id>4198174</relationship_id>
      <predicate>ON</predicate>
      <subject>2862102</subject>
      <object>2862097</object>
    </relationship>
    <relationship>
      <relationship_id>4198175</relationship_id>
      <predicate>ON</predicate>
      <subject>2862103</subject>
      <object>2862097</object>
    </relationship>
    <relationship>
      <relationship_id>4198176</relationship_id>
      <predicate>ON</predicate>
      <subject>3003937</subject>
      <object>2862097</object>
    </relationship>
    <relationship>
      <relationship_id>4198177</relationship_id>
      <predicate>ON</predicate>
      <subject>3759029</subject>
      <object>3493390</object>
    </relationship>
    <relationship>
      <relationship_id>4198178</relationship_id>
      <predicate>ON</predicate>
      <subject>2176295</subject>
      <object>2176294</object>
    </relationship>
    <relationship>
      <relationship_id>4198179</relationship_id>
      <predicate>ON</predicate>
      <subject>2176296</subject>
      <object>2176294</object>
    </relationship>
    <relationship>
      <relationship_id>4198180</relationship_id>
      <predicate>ON</predicate>
      <subject>2176297</subject>
      <object>2176294</object>
    </relationship>
    <relationship>
      <relationship_id>4198181</relationship_id>
      <predicate>ON</predicate>
      <subject>3759030</subject>
      <object>1953016</object>
    </relationship>
    <relationship>
      <relationship_id>4198183</relationship_id>
      <predicate>ON</predicate>
      <subject>2138106</subject>
      <object>2100218</object>
    </relationship>
    <relationship>
      <relationship_id>4198184</relationship_id>
      <predicate>ON</predicate>
      <subject>2138106</subject>
      <object>3759032</object>
    </relationship>
    <relationship>
      <relationship_id>4198182</relationship_id>
      <predicate>ON</predicate>
      <subject>2100218</subject>
      <object>3759032</object>
    </relationship>
    <relationship>
      <relationship_id>4198185</relationship_id>
      <predicate>ON</predicate>
      <subject>2138106</subject>
      <object>3483999</object>
    </relationship>
    <relationship>
      <relationship_id>4198186</relationship_id>
      <predicate>ON</predicate>
      <subject>2623589</subject>
      <object>2138106</object>
    </relationship>
    <relationship>
      <relationship_id>4198187</relationship_id>
      <predicate>ON</predicate>
      <subject>2623589</subject>
      <object>3483999</object>
    </relationship>
    <relationship>
      <relationship_id>4198188</relationship_id>
      <predicate>under</predicate>
      <subject>3283623</subject>
      <object>3759033</object>
    </relationship>
    <relationship>
      <relationship_id>3914906</relationship_id>
      <predicate>covered with</predicate>
      <subject>3483999</subject>
      <object>3643015</object>
    </relationship>
    <relationship>
      <relationship_id>4198189</relationship_id>
      <predicate>IN</predicate>
      <subject>2598967</subject>
      <object>3759034</object>
    </relationship>
    <relationship>
      <relationship_id>4198190</relationship_id>
      <predicate>ON</predicate>
      <subject>3003937</subject>
      <object>3112730</object>
    </relationship>
    <relationship>
      <relationship_id>4198191</relationship_id>
      <predicate>ON</predicate>
      <subject>2862102</subject>
      <object>3112730</object>
    </relationship>
    <relationship>
      <relationship_id>4198192</relationship_id>
      <predicate>ON</predicate>
      <subject>2176294</subject>
      <object>2751342</object>
    </relationship>
    <relationship>
      <relationship_id>3914970</relationship_id>
      <predicate>on</predicate>
      <subject>2862102</subject>
      <object>3643032</object>
    </relationship>
    <relationship>
      <relationship_id>4198194</relationship_id>
      <predicate>IN</predicate>
      <subject>3759035</subject>
      <object>3759036</object>
    </relationship>
    <relationship>
      <relationship_id>4198193</relationship_id>
      <predicate>ON</predicate>
      <subject>3493390</subject>
      <object>3759035</object>
    </relationship>
    <relationship>
      <relationship_id>4198195</relationship_id>
      <predicate>IN</predicate>
      <subject>3483999</subject>
      <object>3759037</object>
    </relationship>
    <relationship>
      <relationship_id>4198196</relationship_id>
      <predicate>hanging from</predicate>
      <subject>1665820</subject>
      <object>1665821</object>
    </relationship>
  </relationships>
  <objects>
    <object>
      <h>26</h>
      <object_id>2138106</object_id>
      <w>27</w>
      <y>180</y>
      <x>132</x>
      <name>tire</name>
    </object>
    <object>
      <attributes>
        <attribute>blue</attribute>
      </attributes>
      <h>70</h>
      <object_id>3483999</object_id>
      <w>165</w>
      <y>144</y>
      <x>1</x>
      <name>car</name>
    </object>
    <object>
      <attributes>
        <attribute>red</attribute>
        <attribute>white</attribute>
      </attributes>
      <name>sign</name>
      <h>89</h>
      <object_id>3003937</object_id>
      <w>81</w>
      <y>277</y>
      <x>133</x>
    </object>
    <object>
      <name>pole</name>
      <h>179</h>
      <object_id>3759021</object_id>
      <w>133</w>
      <y>183</y>
      <x>131</x>
    </object>
    <object>
      <h>67</h>
      <object_id>2862098</object_id>
      <w>62</w>
      <y>66</y>
      <x>357</x>
      <name>sign</name>
    </object>
    <object>
      <name>pole</name>
      <h>80</h>
      <object_id>2949911</object_id>
      <w>124</w>
      <y>115</y>
      <x>253</x>
    </object>
    <object>
      <h>30</h>
      <object_id>2862102</object_id>
      <w>28</w>
      <y>216</y>
      <x>110</x>
      <name>light</name>
    </object>
    <object>
      <name>pole</name>
      <h>36</h>
      <object_id>3759016</object_id>
      <w>90</w>
      <y>183</y>
      <x>159</x>
    </object>
    <object>
      <name>pole</name>
      <h>75</h>
      <object_id>3759024</object_id>
      <w>101</w>
      <y>107</y>
      <x>151</x>
    </object>
    <object>
      <name>sign</name>
      <h>54</h>
      <object_id>2862100</object_id>
      <w>58</w>
      <y>78</y>
      <x>114</x>
    </object>
    <object>
      <name>ground</name>
      <h>187</h>
      <object_id>2135808</object_id>
      <w>495</w>
      <y>186</y>
      <x>2</x>
    </object>
    <object>
      <h>29</h>
      <object_id>2623589</object_id>
      <w>32</w>
      <y>185</y>
      <x>21</x>
      <name>suv wheel</name>
    </object>
    <object>
      <name>vehicle</name>
      <h>70</h>
      <object_id>3759032</object_id>
      <w>166</w>
      <y>140</y>
      <x>0</x>
    </object>
    <object>
      <name>face</name>
      <h>57</h>
      <object_id>2430348</object_id>
      <w>21</w>
      <y>115</y>
      <x>450</x>
    </object>
    <object>
      <name>window</name>
      <h>142</h>
      <object_id>2430349</object_id>
      <w>67</w>
      <y>90</y>
      <x>432</x>
    </object>
    <object>
      <attributes>
        <attribute>brick</attribute>
      </attributes>
      <name>brick wall</name>
      <h>77</h>
      <object_id>3759018</object_id>
      <w>131</w>
      <y>0</y>
      <x>255</x>
    </object>
    <object>
      <name>building</name>
      <h>263</h>
      <object_id>2619141</object_id>
      <w>495</w>
      <y>2</y>
      <x>2</x>
    </object>
    <object>
      <name>window</name>
      <h>20</h>
      <object_id>3759019</object_id>
      <w>39</w>
      <y>148</y>
      <x>79</x>
    </object>
    <object>
      <name>car</name>
      <h>77</h>
      <object_id>2315142</object_id>
      <w>170</w>
      <y>141</y>
      <x>3</x>
    </object>
    <object>
      <name>pole</name>
      <h>30</h>
      <object_id>3759025</object_id>
      <w>90</w>
      <y>184</y>
      <x>160</x>
    </object>
    <object>
      <name>pole</name>
      <h>350</h>
      <object_id>2949207</object_id>
      <w>327</w>
      <y>13</y>
      <x>83</x>
    </object>
    <object>
      <name>pole</name>
      <h>103</h>
      <object_id>3759023</object_id>
      <w>54</w>
      <y>77</y>
      <x>251</x>
    </object>
    <object>
      <name>pole</name>
      <h>113</h>
      <object_id>3759022</object_id>
      <w>154</w>
      <y>80</y>
      <x>255</x>
    </object>
    <object>
      <name>pole</name>
      <h>88</h>
      <object_id>3759020</object_id>
      <w>110</w>
      <y>190</y>
      <x>263</x>
    </object>
    <object>
      <h>56</h>
      <object_id>2176294</object_id>
      <w>49</w>
      <y>206</y>
      <x>164</x>
      <name>signal light</name>
    </object>
    <object>
      <name>pole</name>
      <h>111</h>
      <object_id>3323943</object_id>
      <w>94</w>
      <y>187</y>
      <x>168</x>
    </object>
    <object>
      <attributes>
        <attribute>wooden</attribute>
        <attribute>brown</attribute>
      </attributes>
      <name>box</name>
      <h>75</h>
      <object_id>2135807</object_id>
      <w>105</w>
      <y>212</y>
      <x>42</x>
    </object>
    <object>
      <name>picture</name>
      <h>64</h>
      <object_id>3759035</object_id>
      <w>30</w>
      <y>112</y>
      <x>447</x>
    </object>
    <object>
      <name>building</name>
      <h>197</h>
      <object_id>1794390</object_id>
      <w>330</w>
      <y>20</y>
      <x>164</x>
    </object>
    <object>
      <h>53</h>
      <object_id>3493390</object_id>
      <w>24</w>
      <y>117</y>
      <x>450</x>
      <name>portrait</name>
    </object>
    <object>
      <attributes>
        <attribute>black</attribute>
      </attributes>
      <name>arrow</name>
      <h>24</h>
      <object_id>3759027</object_id>
      <w>40</w>
      <y>318</y>
      <x>151</x>
    </object>
    <object>
      <attributes>
        <attribute>white</attribute>
        <attribute>Red </attribute>
      </attributes>
      <name>sign</name>
      <h>102</h>
      <object_id>2163548</object_id>
      <w>98</w>
      <y>260</y>
      <x>127</x>
    </object>
    <object>
      <attributes>
        <attribute>black</attribute>
      </attributes>
      <name>figure</name>
      <h>27</h>
      <object_id>3514471</object_id>
      <w>31</w>
      <y>82</y>
      <x>121</x>
    </object>
    <object>
      <attributes>
        <attribute>red</attribute>
        <attribute>white</attribute>
      </attributes>
      <name>sign</name>
      <h>59</h>
      <object_id>3514470</object_id>
      <w>60</w>
      <y>75</y>
      <x>111</x>
    </object>
    <object>
      <attributes>
        <attribute>black</attribute>
      </attributes>
      <name>figure</name>
      <h>12</h>
      <object_id>3514472</object_id>
      <w>17</w>
      <y>103</y>
      <x>127</x>
    </object>
    <object>
      <attributes>
        <attribute>red</attribute>
      </attributes>
      <name>box</name>
      <h>11</h>
      <object_id>3759028</object_id>
      <w>20</w>
      <y>106</y>
      <x>379</x>
    </object>
    <object>
      <attributes>
        <attribute>white</attribute>
        <attribute>Blue</attribute>
      </attributes>
      <name>sign</name>
      <h>73</h>
      <object_id>2891655</object_id>
      <w>87</w>
      <y>68</y>
      <x>340</x>
    </object>
    <object>
      <name>graffiti</name>
      <h>37</h>
      <object_id>3361675</object_id>
      <w>51</w>
      <y>134</y>
      <x>118</x>
    </object>
    <object>
      <attributes>
        <attribute>White</attribute>
      </attributes>
      <name>block</name>
      <h>60</h>
      <object_id>3361674</object_id>
      <w>128</w>
      <y>123</y>
      <x>45</x>
    </object>
    <object>
      <attributes>
        <attribute>yellow</attribute>
      </attributes>
      <h>29</h>
      <object_id>1665820</object_id>
      <w>55</w>
      <y>0</y>
      <x>347</x>
      <name>banner</name>
    </object>
    <object>
      <name>sculpture</name>
      <h>361</h>
      <object_id>2862097</object_id>
      <w>333</w>
      <y>1</y>
      <x>94</x>
    </object>
    <object>
      <name>light</name>
      <h>28</h>
      <object_id>2862101</object_id>
      <w>41</w>
      <y>271</y>
      <x>364</x>
    </object>
    <object>
      <name>light</name>
      <h>73</h>
      <object_id>2862103</object_id>
      <w>52</w>
      <y>16</y>
      <x>294</x>
    </object>
    <object>
      <name>light</name>
      <h>40</h>
      <object_id>3759029</object_id>
      <w>24</w>
      <y>111</y>
      <x>448</x>
    </object>
    <object>
      <name>light</name>
      <h>24</h>
      <object_id>2176295</object_id>
      <w>17</w>
      <y>210</y>
      <x>200</x>
    </object>
    <object>
      <name>light</name>
      <h>16</h>
      <object_id>2176296</object_id>
      <w>15</w>
      <y>230</y>
      <x>190</x>
    </object>
    <object>
      <name>light</name>
      <h>23</h>
      <object_id>2176297</object_id>
      <w>20</w>
      <y>241</y>
      <x>174</x>
    </object>
    <object>
      <name>grafitti</name>
      <h>16</h>
      <object_id>3759030</object_id>
      <w>52</w>
      <y>234</y>
      <x>56</x>
    </object>
    <object>
      <attributes>
        <attribute>small</attribute>
      </attributes>
      <name>box</name>
      <h>60</h>
      <object_id>1953016</object_id>
      <w>97</w>
      <y>215</y>
      <x>42</x>
    </object>
    <object>
      <name>front tire</name>
      <h>26</h>
      <object_id>2100218</object_id>
      <w>24</w>
      <y>180</y>
      <x>133</x>
    </object>
    <object>
      <attributes>
        <attribute>brick</attribute>
      </attributes>
      <name>wall</name>
      <h>122</h>
      <object_id>3283623</object_id>
      <w>145</w>
      <y>130</y>
      <x>248</x>
    </object>
    <object>
      <name>windows</name>
      <h>74</h>
      <object_id>3759033</object_id>
      <w>126</w>
      <y>58</y>
      <x>263</x>
    </object>
    <object>
      <name>graffiti</name>
      <h>22</h>
      <object_id>3643015</object_id>
      <w>42</w>
      <y>137</y>
      <x>121</x>
    </object>
    <object>
      <attributes>
        <attribute>black</attribute>
      </attributes>
      <name>post</name>
      <h>48</h>
      <object_id>2598967</object_id>
      <w>18</w>
      <y>179</y>
      <x>37</x>
    </object>
    <object>
      <name>concrete</name>
      <h>178</h>
      <object_id>3759034</object_id>
      <w>484</w>
      <y>194</y>
      <x>12</x>
    </object>
    <object>
      <name>ground</name>
      <h>45</h>
      <object_id>3112730</object_id>
      <w>73</w>
      <y>276</y>
      <x>239</x>
    </object>
    <object>
      <name>ground</name>
      <h>165</h>
      <object_id>2751342</object_id>
      <w>497</w>
      <y>207</y>
      <x>2</x>
    </object>
    <object>
      <name>ground</name>
      <h>120</h>
      <object_id>3643032</object_id>
      <w>192</w>
      <y>252</y>
      <x>201</x>
    </object>
    <object>
      <name>window</name>
      <h>137</h>
      <object_id>3759036</object_id>
      <w>71</w>
      <y>93</y>
      <x>427</x>
    </object>
    <object>
      <name>street</name>
      <h>165</h>
      <object_id>3759037</object_id>
      <w>474</w>
      <y>208</y>
      <x>24</x>
    </object>
    <object>
      <name>ceiling</name>
      <h>8</h>
      <object_id>1665821</object_id>
      <w>303</w>
      <y>0</y>
      <x>192</x>
    </object>
  </objects>
  <captions type="train">
    <caption>A piece of artwork was made from a variety of street signs.</caption>
      <caption>A street pole lies broken, strewn across a sidewalk.</caption>
      <caption>A street sign monstrosity siting in a creepy alley.</caption>
      <caption>Unusual outside picture of a building, and a bunch of streets signs crossed over each other.</caption>
      <caption>An art piece with various traffic signs attached it.</caption>
    </captions>
</image>