<image>
  <image-id>2369922</image-id>
  <coco-id>311895</coco-id>
  <relationships>
    <relationship>
      <relationship_id>1552636</relationship_id>
      <predicate>ON</predicate>
      <subject>608080</subject>
      <object>608081</object>
    </relationship>
    <relationship>
      <relationship_id>1552637</relationship_id>
      <predicate>ON</predicate>
      <subject>608080</subject>
      <object>608081</object>
    </relationship>
    <relationship>
      <relationship_id>1552638</relationship_id>
      <predicate>ON</predicate>
      <subject>608080</subject>
      <object>608081</object>
    </relationship>
    <relationship>
      <relationship_id>1552639</relationship_id>
      <predicate>ON</predicate>
      <subject>608080</subject>
      <object>608081</object>
    </relationship>
    <relationship>
      <relationship_id>1552640</relationship_id>
      <predicate>ON</predicate>
      <subject>608080</subject>
      <object>608081</object>
    </relationship>
    <relationship>
      <relationship_id>1552641</relationship_id>
      <predicate>ON</predicate>
      <subject>608082</subject>
      <object>608081</object>
    </relationship>
    <relationship>
      <relationship_id>1552642</relationship_id>
      <predicate>ON</predicate>
      <subject>608082</subject>
      <object>608081</object>
    </relationship>
    <relationship>
      <relationship_id>1552643</relationship_id>
      <predicate>ON</predicate>
      <subject>608082</subject>
      <object>608081</object>
    </relationship>
    <relationship>
      <relationship_id>1552644</relationship_id>
      <predicate>ON</predicate>
      <subject>608082</subject>
      <object>608081</object>
    </relationship>
    <relationship>
      <relationship_id>1552645</relationship_id>
      <predicate>ON</predicate>
      <subject>608082</subject>
      <object>608081</object>
    </relationship>
    <relationship>
      <relationship_id>1552646</relationship_id>
      <predicate>ON</predicate>
      <subject>608083</subject>
      <object>608081</object>
    </relationship>
    <relationship>
      <relationship_id>1552647</relationship_id>
      <predicate>ON</predicate>
      <subject>608083</subject>
      <object>608081</object>
    </relationship>
    <relationship>
      <relationship_id>1552648</relationship_id>
      <predicate>ON</predicate>
      <subject>608083</subject>
      <object>608081</object>
    </relationship>
    <relationship>
      <relationship_id>1552649</relationship_id>
      <predicate>ON</predicate>
      <subject>608083</subject>
      <object>608081</object>
    </relationship>
    <relationship>
      <relationship_id>1552650</relationship_id>
      <predicate>ON</predicate>
      <subject>608083</subject>
      <object>608081</object>
    </relationship>
    <relationship>
      <relationship_id>1552651</relationship_id>
      <predicate>ON</predicate>
      <subject>608084</subject>
      <object>608085</object>
    </relationship>
    <relationship>
      <relationship_id>1552652</relationship_id>
      <predicate>ON</predicate>
      <subject>608084</subject>
      <object>608085</object>
    </relationship>
    <relationship>
      <relationship_id>1552653</relationship_id>
      <predicate>ON</predicate>
      <subject>608084</subject>
      <object>608085</object>
    </relationship>
    <relationship>
      <relationship_id>1552654</relationship_id>
      <predicate>ON</predicate>
      <subject>608084</subject>
      <object>608085</object>
    </relationship>
    <relationship>
      <relationship_id>1552655</relationship_id>
      <predicate>ON</predicate>
      <subject>608084</subject>
      <object>608085</object>
    </relationship>
    <relationship>
      <relationship_id>1552656</relationship_id>
      <predicate>ON</predicate>
      <subject>608086</subject>
      <object>608085</object>
    </relationship>
    <relationship>
      <relationship_id>1552657</relationship_id>
      <predicate>ON</predicate>
      <subject>608086</subject>
      <object>608085</object>
    </relationship>
    <relationship>
      <relationship_id>1552658</relationship_id>
      <predicate>ON</predicate>
      <subject>608086</subject>
      <object>608085</object>
    </relationship>
    <relationship>
      <relationship_id>1552659</relationship_id>
      <predicate>ON</predicate>
      <subject>608086</subject>
      <object>608085</object>
    </relationship>
    <relationship>
      <relationship_id>1552660</relationship_id>
      <predicate>ON</predicate>
      <subject>608086</subject>
      <object>608085</object>
    </relationship>
  </relationships>
  <objects>
    <object>
      <name>paper</name>
      <h>96</h>
      <object_id>608080</object_id>
      <w>38</w>
      <y>130</y>
      <x>228</x>
    </object>
    <object>
      <name>refrigerator</name>
      <h>317</h>
      <object_id>608081</object_id>
      <w>274</w>
      <y>4</y>
      <x>177</x>
    </object>
    <object>
      <attributes>
        <attribute>colorful</attribute>
      </attributes>
      <name>letters</name>
      <h>119</h>
      <object_id>608082</object_id>
      <w>50</w>
      <y>205</y>
      <x>368</x>
    </object>
    <object>
      <name>picture</name>
      <h>39</h>
      <object_id>608083</object_id>
      <w>44</w>
      <y>91</y>
      <x>308</x>
    </object>
    <object>
      <attributes>
        <attribute>white</attribute>
      </attributes>
      <name>jar</name>
      <h>47</h>
      <object_id>608084</object_id>
      <w>44</w>
      <y>111</y>
      <x>153</x>
    </object>
    <object>
      <attributes>
        <attribute>white</attribute>
      </attributes>
      <name>microwave oven</name>
      <h>92</h>
      <object_id>608085</object_id>
      <w>200</w>
      <y>177</y>
      <x>11</x>
    </object>
    <object>
      <attributes>
        <attribute>floral</attribute>
      </attributes>
      <name>plates</name>
      <h>31</h>
      <object_id>608086</object_id>
      <w>78</w>
      <y>138</y>
      <x>76</x>
    </object>
  </objects>
  <captions type="train">
    <caption>The refrigerator next to the microwave has many stickers on the door.</caption>
      <caption>A microwave and a refrigerator in a room.</caption>
      <caption>A kitchen is all white with marble contertops.</caption>
      <caption>This is picture of a refrigerator in a kitchen.</caption>
      <caption>A kitchen refrigerator has several magnets on it.</caption>
    </captions>
</image>