<image>
  <image-id>2381975</image-id>
  <coco-id>32124</coco-id>
  <relationships>
    <relationship>
      <relationship_id>1860486</relationship_id>
      <predicate>sitting on</predicate>
      <subject>700419</subject>
      <object>700420</object>
    </relationship>
    <relationship>
      <relationship_id>1860487</relationship_id>
      <predicate>near</predicate>
      <subject>700421</subject>
      <object>700419</object>
    </relationship>
    <relationship>
      <relationship_id>1860488</relationship_id>
      <predicate>has</predicate>
      <subject>700419</subject>
      <object>700422</object>
    </relationship>
    <relationship>
      <relationship_id>1860489</relationship_id>
      <predicate>leaning on</predicate>
      <subject>700423</subject>
      <object>700424</object>
    </relationship>
    <relationship>
      <relationship_id>1860490</relationship_id>
      <predicate>wears</predicate>
      <subject>700425</subject>
      <object>700426</object>
    </relationship>
    <relationship>
      <relationship_id>1860491</relationship_id>
      <predicate>has</predicate>
      <subject>700426</subject>
      <object>700427</object>
    </relationship>
    <relationship>
      <relationship_id>1860492</relationship_id>
      <predicate>grow on</predicate>
      <subject>700428</subject>
      <object>700420</object>
    </relationship>
    <relationship>
      <relationship_id>1860493</relationship_id>
      <predicate>wears a</predicate>
      <subject>700425</subject>
      <object>700429</object>
    </relationship>
    <relationship>
      <relationship_id>1860494</relationship_id>
      <predicate>wears a</predicate>
      <subject>700430</subject>
      <object>700431</object>
    </relationship>
    <relationship>
      <relationship_id>1860495</relationship_id>
      <predicate>wears</predicate>
      <subject>700430</subject>
      <object>700432</object>
    </relationship>
    <relationship>
      <relationship_id>1860496</relationship_id>
      <predicate>stands near</predicate>
      <subject>700433</subject>
      <object>700434</object>
    </relationship>
    <relationship>
      <relationship_id>1860497</relationship_id>
      <predicate>sits on</predicate>
      <subject>700419</subject>
      <object>700420</object>
    </relationship>
    <relationship>
      <relationship_id>1860498</relationship_id>
      <predicate>sits on</predicate>
      <subject>700421</subject>
      <object>700435</object>
    </relationship>
    <relationship>
      <relationship_id>1860499</relationship_id>
      <predicate>leans on</predicate>
      <subject>700423</subject>
      <object>700424</object>
    </relationship>
    <relationship>
      <relationship_id>1860500</relationship_id>
      <predicate>has a</predicate>
      <subject>700426</subject>
      <object>700427</object>
    </relationship>
    <relationship>
      <relationship_id>1860501</relationship_id>
      <predicate>has</predicate>
      <subject>700425</subject>
      <object>700429</object>
    </relationship>
    <relationship>
      <relationship_id>1860502</relationship_id>
      <predicate>has</predicate>
      <subject>700433</subject>
      <object>700436</object>
    </relationship>
    <relationship>
      <relationship_id>1860503</relationship_id>
      <predicate>wears</predicate>
      <subject>700425</subject>
      <object>700429</object>
    </relationship>
    <relationship>
      <relationship_id>1860504</relationship_id>
      <predicate>sits on</predicate>
      <subject>700421</subject>
      <object>700435</object>
    </relationship>
    <relationship>
      <relationship_id>1860505</relationship_id>
      <predicate>ON</predicate>
      <subject>700423</subject>
      <object>700439</object>
    </relationship>
    <relationship>
      <relationship_id>1860506</relationship_id>
      <predicate>wears</predicate>
      <subject>700425</subject>
      <object>700429</object>
    </relationship>
    <relationship>
      <relationship_id>1860507</relationship_id>
      <predicate>has</predicate>
      <subject>700425</subject>
      <object>700440</object>
    </relationship>
    <relationship>
      <relationship_id>1860508</relationship_id>
      <predicate>has</predicate>
      <subject>700433</subject>
      <object>700441</object>
    </relationship>
    <relationship>
      <relationship_id>1860509</relationship_id>
      <predicate>of old man has</predicate>
      <subject>700441</subject>
      <object>700436</object>
    </relationship>
    <relationship>
      <relationship_id>1860510</relationship_id>
      <predicate>wears</predicate>
      <subject>700430</subject>
      <object>700442</object>
    </relationship>
    <relationship>
      <relationship_id>1860511</relationship_id>
      <predicate>wears</predicate>
      <subject>700430</subject>
      <object>700432</object>
    </relationship>
    <relationship>
      <relationship_id>1860512</relationship_id>
      <predicate>wears</predicate>
      <subject>700425</subject>
      <object>700426</object>
    </relationship>
    <relationship>
      <relationship_id>1860513</relationship_id>
      <predicate>has</predicate>
      <subject>700426</subject>
      <object>700427</object>
    </relationship>
    <relationship>
      <relationship_id>1860514</relationship_id>
      <predicate>hanging on</predicate>
      <subject>700443</subject>
      <object>700437</object>
    </relationship>
    <relationship>
      <relationship_id>1860515</relationship_id>
      <predicate>wears</predicate>
      <subject>700425</subject>
      <object>700429</object>
    </relationship>
    <relationship>
      <relationship_id>1860516</relationship_id>
      <predicate>sits on</predicate>
      <subject>700419</subject>
      <object>700420</object>
    </relationship>
    <relationship>
      <relationship_id>1860517</relationship_id>
      <predicate>sits on</predicate>
      <subject>700419</subject>
      <object>700420</object>
    </relationship>
    <relationship>
      <relationship_id>1860525</relationship_id>
      <predicate>sits o</predicate>
      <subject>700419</subject>
      <object>700420</object>
    </relationship>
  </relationships>
  <objects>
    <object>
      <attributes>
        <attribute>sitting</attribute>
        <attribute>looking</attribute>
      </attributes>
      <name>woman</name>
      <h>140</h>
      <object_id>700419</object_id>
      <w>81</w>
      <y>169</y>
      <x>235</x>
    </object>
    <object>
      <name>curb</name>
      <h>68</h>
      <object_id>700420</object_id>
      <w>325</w>
      <y>259</y>
      <x>116</x>
    </object>
    <object>
      <attributes>
        <attribute>black</attribute>
        <attribute>sitting</attribute>
      </attributes>
      <name>backpack</name>
      <h>57</h>
      <object_id>700421</object_id>
      <w>54</w>
      <y>256</y>
      <x>262</x>
    </object>
    <object>
      <name>tattoos</name>
      <h>32</h>
      <object_id>700422</object_id>
      <w>14</w>
      <y>208</y>
      <x>246</x>
    </object>
    <object>
      <attributes>
        <attribute>blue</attribute>
        <attribute>leaning</attribute>
      </attributes>
      <name>bicycle</name>
      <h>115</h>
      <object_id>700423</object_id>
      <w>107</w>
      <y>113</y>
      <x>330</x>
    </object>
    <object>
      <name>wall</name>
      <h>120</h>
      <object_id>700424</object_id>
      <w>328</w>
      <y>119</y>
      <x>114</x>
    </object>
    <object>
      <attributes>
        <attribute>standing</attribute>
      </attributes>
      <name>man</name>
      <h>347</h>
      <object_id>700425</object_id>
      <w>131</w>
      <y>3</y>
      <x>2</x>
    </object>
    <object>
      <name>shirt</name>
      <h>249</h>
      <object_id>700426</object_id>
      <w>128</w>
      <y>99</y>
      <x>2</x>
    </object>
    <object>
      <attributes>
        <attribute>bicycle</attribute>
        <attribute>bike</attribute>
      </attributes>
      <name>design</name>
      <h>150</h>
      <object_id>700427</object_id>
      <w>90</w>
      <y>199</y>
      <x>2</x>
    </object>
    <object>
      <name>weeds</name>
      <h>25</h>
      <object_id>700428</object_id>
      <w>107</w>
      <y>265</y>
      <x>122</x>
    </object>
    <object>
      <attributes>
        <attribute>blue</attribute>
      </attributes>
      <name>hat</name>
      <h>71</h>
      <object_id>700429</object_id>
      <w>67</w>
      <y>6</y>
      <x>0</x>
    </object>
    <object>
      <attributes>
        <attribute>standing</attribute>
        <attribute>stnading</attribute>
      </attributes>
      <name>woman</name>
      <h>305</h>
      <object_id>700430</object_id>
      <w>77</w>
      <y>44</y>
      <x>422</x>
    </object>
    <object>
      <attributes>
        <attribute>green</attribute>
        <attribute>shortsleeved</attribute>
      </attributes>
      <name>shirt</name>
      <h>134</h>
      <object_id>700431</object_id>
      <w>68</w>
      <y>106</y>
      <x>432</x>
    </object>
    <object>
      <name>backpack</name>
      <h>147</h>
      <object_id>700432</object_id>
      <w>99</w>
      <y>109</y>
      <x>401</x>
    </object>
    <object>
      <attributes>
        <attribute>standing</attribute>
      </attributes>
      <name>old man</name>
      <h>222</h>
      <object_id>700433</object_id>
      <w>78</w>
      <y>23</y>
      <x>149</x>
    </object>
    <object>
      <attributes>
        <attribute>leaning</attribute>
      </attributes>
      <name>bicycle</name>
      <h>132</h>
      <object_id>700434</object_id>
      <w>68</w>
      <y>110</y>
      <x>110</x>
    </object>
    <object>
      <name>street</name>
      <h>64</h>
      <object_id>700435</object_id>
      <w>393</w>
      <y>286</y>
      <x>106</x>
    </object>
    <object>
      <name>hat</name>
      <h>19</h>
      <object_id>700436</object_id>
      <w>37</w>
      <y>23</y>
      <x>179</x>
    </object>
    <object>
      <name>sidewalk</name>
      <h>76</h>
      <object_id>700439</object_id>
      <w>314</w>
      <y>214</y>
      <x>119</x>
    </object>
    <object>
      <name>head</name>
      <h>107</h>
      <object_id>700440</object_id>
      <w>66</w>
      <y>7</y>
      <x>0</x>
    </object>
    <object>
      <name>head</name>
      <h>42</h>
      <object_id>700441</object_id>
      <w>32</w>
      <y>24</y>
      <x>179</x>
    </object>
    <object>
      <name>glasses</name>
      <h>21</h>
      <object_id>700442</object_id>
      <w>23</w>
      <y>70</y>
      <x>476</x>
    </object>
    <object>
      <name>banner</name>
      <h>144</h>
      <object_id>700443</object_id>
      <w>100</w>
      <y>3</y>
      <x>248</x>
    </object>
    <object>
      <attributes>
        <attribute>chain link</attribute>
        <attribute>metal</attribute>
      </attributes>
      <name>fence</name>
      <h>136</h>
      <object_id>700437</object_id>
      <w>499</w>
      <y>2</y>
      <x>1</x>
    </object>
  </objects>
  <captions type="train">
    <caption>A pretty young lady sitting on a sidewalk next to an older man.</caption>
      <caption>A young woman sitting on the curb while others stand nearby.</caption>
      <caption>A woman sitting on a curb with a backpack by her feet.</caption>
      <caption>a group of people standing near a person sitting on a curb</caption>
      <caption>The young woman sits on the curb of the sidewalk </caption>
    </captions>
</image>