<image>
  <image-id>2406828</image-id>
  <coco-id>42701</coco-id>
  <relationships>
    <relationship>
      <relationship_id>4668097</relationship_id>
      <predicate>with</predicate>
      <subject>4265083</subject>
      <object>4079669</object>
    </relationship>
    <relationship>
      <relationship_id>4668098</relationship_id>
      <predicate>with</predicate>
      <subject>4265083</subject>
      <object>4079669</object>
    </relationship>
    <relationship>
      <relationship_id>4563553</relationship_id>
      <predicate>ON</predicate>
      <subject>4008173</subject>
      <object>4008172</object>
    </relationship>
    <relationship>
      <relationship_id>4563556</relationship_id>
      <predicate>standing</predicate>
      <subject>4008342</subject>
      <object>4265083</object>
    </relationship>
    <relationship>
      <relationship_id>4563557</relationship_id>
      <predicate>surrounding</predicate>
      <subject>4265083</subject>
      <object>4079666</object>
    </relationship>
    <relationship>
      <relationship_id>4563558</relationship_id>
      <predicate>surrounding</predicate>
      <subject>4008183</subject>
      <object>4079666</object>
    </relationship>
    <relationship>
      <relationship_id>4563561</relationship_id>
      <predicate>ON</predicate>
      <subject>4008189</subject>
      <object>4008190</object>
    </relationship>
    <relationship>
      <relationship_id>4593403</relationship_id>
      <predicate>IN</predicate>
      <subject>4079663</subject>
      <object>4142496</object>
    </relationship>
    <relationship>
      <relationship_id>4593404</relationship_id>
      <predicate>IN</predicate>
      <subject>4079665</subject>
      <object>4079666</object>
    </relationship>
    <relationship>
      <relationship_id>4593405</relationship_id>
      <predicate>has</predicate>
      <subject>4265083</subject>
      <object>4079669</object>
    </relationship>
    <relationship>
      <relationship_id>4563630</relationship_id>
      <predicate>behind</predicate>
      <subject>4008342</subject>
      <object>4265083</object>
    </relationship>
  </relationships>
  <objects>
    <object>
      <attributes>
        <attribute>green</attribute>
      </attributes>
      <name>tree</name>
      <h>289</h>
      <object_id>4265083</object_id>
      <w>296</w>
      <y>84</y>
      <x>18</x>
    </object>
    <object>
      <h>247</h>
      <object_id>4079669</object_id>
      <w>360</w>
      <y>3</y>
      <x>1</x>
      <name>leaves</name>
    </object>
    <object>
      <name>plums</name>
      <h>34</h>
      <object_id>4008173</object_id>
      <w>41</w>
      <y>332</y>
      <x>307</x>
    </object>
    <object>
      <attributes>
        <attribute>small </attribute>
      </attributes>
      <name>bush</name>
      <h>76</h>
      <object_id>4008172</object_id>
      <w>189</w>
      <y>289</y>
      <x>258</x>
    </object>
    <object>
      <attributes>
        <attribute>white</attribute>
      </attributes>
      <h>47</h>
      <object_id>4008342</object_id>
      <w>75</w>
      <y>240</y>
      <x>112</x>
      <name>cow</name>
    </object>
    <object>
      <h>143</h>
      <object_id>4079666</object_id>
      <w>496</w>
      <y>229</y>
      <x>1</x>
      <name>field</name>
    </object>
    <object>
      <attributes>
        <attribute>wooden</attribute>
      </attributes>
      <name>stake</name>
      <h>40</h>
      <object_id>4008183</object_id>
      <w>28</w>
      <y>240</y>
      <x>284</x>
    </object>
    <object>
      <attributes>
        <attribute>white </attribute>
      </attributes>
      <name>marker</name>
      <h>10</h>
      <object_id>4008189</object_id>
      <w>10</w>
      <y>256</y>
      <x>293</x>
    </object>
    <object>
      <name>stake</name>
      <h>45</h>
      <object_id>4008190</object_id>
      <w>13</w>
      <y>237</y>
      <x>290</x>
    </object>
    <object>
      <attributes>
        <attribute>white</attribute>
        <attribute>fluffy</attribute>
      </attributes>
      <name>clouds</name>
      <h>59</h>
      <object_id>4079663</object_id>
      <w>135</w>
      <y>153</y>
      <x>353</x>
    </object>
    <object>
      <h>116</h>
      <object_id>4142496</object_id>
      <w>499</w>
      <y>0</y>
      <x>0</x>
      <name>blue sky</name>
    </object>
    <object>
      <attributes>
        <attribute>brown</attribute>
      </attributes>
      <name>cow</name>
      <h>61</h>
      <object_id>4079665</object_id>
      <w>82</w>
      <y>226</y>
      <x>264</x>
    </object>
  </objects>
  <captions type="train">
    <caption>A herd of cattle standing under a leafy green tree.</caption>
      <caption>Two cows out in the pasture enjoy the afternoon.</caption>
      <caption>Cattle grazing in the tall grass with lone birch tree.</caption>
      <caption>Cows are standing in the grass near a tree.</caption>
      <caption>two cow grazing in a field with a tree beside them</caption>
    </captions>
</image>